{"sision_learners_8_East":[{"name":"ANN WAMBOI"},{"name":"ANNITA WANJIKU"},{"name":"BRIAN NJUGUNA"},{"name":"DAVID MUIRURI"},{"name":"ELIZABETH NJOKI"},{"name":"ELIZABETH WAIRIM"},{"name":"ESTHER MUTHONI"},{"name":"ESTHER NJERI"},{"name":"FAITH NYOKABI"},{"name":"FAITH WAIRIMU"},{"name":"GLADYS WANGOI"},{"name":"GWANDARU PETER"},{"name":"IAN GIKONYO"},{"name":"IAN WAINAINA"},{"name":"JOSEPH NGUGI"},{"name":"JOSEPH WATHIGO"},{"name":"JOY MURUGI"},{"name":"JOY NYAMBURA"},{"name":"JOYLINE GATHIRA"},{"name":"LINET WAIRIMU"},{"name":"MARY WANJIKU"},{"name":"MARYAGNESS W"},{"name":"NAOMI NJERI"},{"name":"ROSEMARY WAIRIM"},{"name":"RUTH WANJIRU"},{"name":"SAMUEL KAMAU"},{"name":"SAMUEL MBURU"},{"name":"STEPHEN NJUGUNA"},{"name":"STEPHEN WAINAINA"},{"name":"SUSAN NJAMBI"},{"name":"VICTOR KIMANI"}]}